Workbook
Name Slicer_Brand: #N/A
Name Slicer_Category: #N/A
Name Slicer_Dealer_Name: #N/A
Name Slicer_Month: #N/A
Name Slicer_Region: #N/A

Sheet BrandPerformance
A3: Row Labels | B3: Sum of Units Sold | C3: Sum of Revenue | D3: Sum of Profit | F3: Row Labels | G3: Sum of Revenue
A4: BMW | B4: 4 | C4: 240000 | D4: 48000 | F4: BMW | G4: 240000
A5: Ford | B5: 4 | C5: 160000 | D5: 28000 | F5: Ford | G5: 160000
A6: Honda | B6: 4 | C6: 112000 | D6: 24000 | F6: Honda | G6: 112000
A7: Hyundai | B7: 4 | C7: 100000 | D7: 20000 | F7: Hyundai | G7: 100000
A8: Toyota | B8: 4 | C8: 120000 | D8: 24000 | F8: Toyota | G8: 120000
A9: Grand Total | B9: 20 | C9: 732000 | D9: 144000 | F9: Grand Total | G9: 732000
A13: Row Labels | B13: Sum of Units Sold
A14: BMW | B14: 4
A15: Ford | B15: 4
A16: Honda | B16: 4
A17: Hyundai | B17: 4
A18: Toyota | B18: 4
A19: Grand Total | B19: 20
A26: Row Labels | B26: Sum of Profit
A27: BMW | B27: 48000
A28: Ford | B28: 28000
A29: Honda | B29: 24000
A30: Hyundai | B30: 20000
A31: Toyota | B31: 24000
A32: Grand Total | B32: 144000

Sheet ModelPerformance
A3: Row Labels | B3: Sum of Units Sold | C3: Sum of Revenue | D3: Sum of Profit | F3: Row Labels | G3: Sum of Revenue
A4: CR-V | B4: 4 | C4: 112000 | D4: 24000 | F4: CR-V | G4: 112000
A5: F-150 | B5: 4 | C5: 160000 | D5: 28000 | F5: F-150 | G5: 160000
A6: RAV4 | B6: 4 | C6: 120000 | D6: 24000 | F6: RAV4 | G6: 120000
A7: Tucson | B7: 4 | C7: 100000 | D7: 20000 | F7: Tucson | G7: 100000
A8: X5 | B8: 4 | C8: 240000 | D8: 48000 | F8: X5 | G8: 240000
A9: Grand Total | B9: 20 | C9: 732000 | D9: 144000 | F9: Grand Total | G9: 732000
A14: Row Labels | B14: Sum of Units Sold
A15: CR-V | B15: 4
A16: F-150 | B16: 4 | G16: Row Labels | H16: Sum of Profit
A17: RAV4 | B17: 4 | G17: CR-V | H17: 24000
A18: Tucson | B18: 4 | G18: F-150 | H18: 28000
A19: X5 | B19: 4 | G19: RAV4 | H19: 24000
A20: Grand Total | B20: 20 | G20: Tucson | H20: 20000
G21: X5 | H21: 48000
G22: Grand Total | H22: 144000

Sheet SalesTrends
A3: Row Labels | B3: Sum of Revenue | C3: Sum of Units Sold | D3: Sum of Profit | G3: Row Labels | H3: Sum of Revenue
A4: January | B4: 123000 | C4: 4 | D4: 24000 | G4: January | H4: 123000
A5: February | B5: 158000 | C5: 4 | D5: 31000 | G5: February | H5: 158000
A6: March | B6: 143000 | C6: 4 | D6: 29000 | G6: March | H6: 143000
A7: April | B7: 155000 | C7: 4 | D7: 30000 | G7: April | H7: 155000
A8: May | B8: 153000 | C8: 4 | D8: 30000 | G8: May | H8: 153000
A9: Grand Total | B9: 732000 | C9: 20 | D9: 144000 | G9: Grand Total | H9: 732000
A14: Row Labels | B14: Sum of Units Sold
A15: January | B15: 4
A16: February | B16: 4
A17: March | B17: 4 | H17: Row Labels | I17: Sum of Profit
A18: April | B18: 4 | H18: January | I18: 24000
A19: May | B19: 4 | H19: February | I19: 31000
A20: Grand Total | B20: 20 | H20: March | I20: 29000
H21: April | I21: 30000
H22: May | I22: 30000
H23: Grand Total | I23: 144000

Sheet DealerAnlytics
A3: Row Labels | B3: Sum of Target Units | C3: Sum of Units Sold | D3: Sum of Revenue | E3: Sum of Profit | G3: Row Labels | H3: Sum of Revenue
A4: Apex Motors | B4: 3000 | C4: 3 | D4: 118000 | E4: 24000 | G4: Apex Motors | H4: 118000
A5: City Auto | B5: 1750 | C5: 2 | D5: 58000 | E5: 12000 | G5: City Auto | H5: 58000
A6: Metro Wheels | B6: 7600 | C6: 3 | D6: 93000 | E6: 18000 | G6: Metro Wheels | H6: 93000
A7: Prime Auto | B7: 2700 | C7: 3 | D7: 98000 | E7: 19000 | G7: Prime Auto | H7: 98000
A8: Royal Motors | B8: 3100 | C8: 3 | D8: 125000 | E8: 24000 | G8: Royal Motors | H8: 125000
A9: Speed Auto | B9: 1450 | C9: 2 | D9: 65000 | E9: 12000 | G9: Speed Auto | H9: 65000
A10: Star Motors | B10: 2100 | C10: 2 | D10: 85000 | E10: 17000 | G10: Star Motors | H10: 85000
A11: United Wheels | B11: 1650 | C11: 2 | D11: 90000 | E11: 18000 | G11: United Wheels | H11: 90000
A12: Grand Total | B12: 23350 | C12: 20 | D12: 732000 | E12: 144000 | G12: Grand Total | H12: 732000
A15: Row Labels | B15: Sum of Target Units | H15: Row Labels | I15: Sum of CSAT Score
A16: Apex Motors | B16: 3000 | H16: Apex Motors | I16: 14.3
A17: City Auto | B17: 1750 | H17: City Auto | I17: 9.1
A18: Metro Wheels | B18: 7600 | H18: Metro Wheels | I18: 13.8
A19: Prime Auto | B19: 2700 | H19: Prime Auto | I19: 13.5
A20: Royal Motors | B20: 3100 | H20: Royal Motors | I20: 13.9
A21: Speed Auto | B21: 1450 | H21: Speed Auto | I21: 8.9
A22: Star Motors | B22: 2100 | H22: Star Motors | I22: 9.5
A23: United Wheels | B23: 1650 | H23: United Wheels | I23: 9.4
A24: Grand Total | B24: 23350 | H24: Grand Total | I24: 92.4
A28: Row Labels | B28: Sum of Target Achievement %
A29: Apex Motors | B29: 3
A30: City Auto | B30: 2
A31: Metro Wheels | B31: 3
A32: Prime Auto | B32: 3
A33: Royal Motors | B33: 3
A34: Speed Auto | B34: 2
A35: Star Motors | B35: 2
A36: United Wheels | B36: 2
A37: Grand Total | B37: 20

Sheet CustomerDemographic
A3: Row Labels | B3: Count of Customer ID | D3: Row Labels | E3: Count of Customer ID
A4: Female | B4: 8 | D4: Female | E4: 8
A5: Male | B5: 12 | D5: Male | E5: 12
A6: Grand Total | B6: 20 | D6: Grand Total | E6: 20
A9: Row Labels | B9: Sum of Customer Age
A10: Female | B10: 272
A11: Male | B11: 489
A12: Grand Total | B12: 761
A21: Row Labels | B21: Count of Occupation
A22: Female | B22: 8
A23: Male | B23: 12
A24: Grand Total | B24: 20

Sheet RegionalSales
A3: Row Labels | B3: Sum of Revenue | C3: Sum of Units Sold | D3: Sum of Profit | H3: Row Labels | I3: Sum of Units Sold
A4: East | B4: 183000 | C4: 5 | D4: 36000 | H4: East | I4: 5
A5: North | B5: 183000 | C5: 5 | D5: 36000 | H5: North | I5: 5
A6: South | B6: 183000 | C6: 5 | D6: 36000 | H6: South | I6: 5
A7: West | B7: 183000 | C7: 5 | D7: 36000 | H7: West | I7: 5
A8: Grand Total | B8: 732000 | C8: 20 | D8: 144000 | H8: Grand Total | I8: 20
A17: Row Labels | B17: Sum of Profit
A18: East | B18: 36000
A19: North | B19: 36000
A20: South | B20: 36000
A21: West | B21: 36000
A22: Grand Total | B22: 144000

Sheet ServiceAnalytics
A3: Row Labels | B3: Sum of Service Cost | C3: Sum of CSAT Score | D3: Count of Service Type | E3: Row Labels | F3: Sum of Service Cost
A4: Brake Service | B4: 1050 | C4: 13.8 | D4: 3 | E4: Brake Service | F4: 1050
A5: Engine Check | B5: 900 | C5: 13.2 | D5: 3 | E5: Engine Check | F5: 900
A6: Full Service | B6: 2000 | C6: 19.5 | D6: 4 | E6: Full Service | F6: 2000
A7: General Service | B7: 750 | C7: 13.3 | D7: 3 | E7: General Service | F7: 750
A8: Oil Change | B8: 1050 | C8: 32.6 | D8: 7 | E8: Oil Change | F8: 1050
A9: Grand Total | B9: 5750 | C9: 92.4 | D9: 20 | E9: Grand Total | F9: 5750
A13: Row Labels | B13: Sum of CSAT Score
A14: Brake Service | B14: 13.8
A15: Engine Check | B15: 13.2
A16: Full Service | B16: 19.5 | G16: Row Labels | H16: Count of Service Type
A17: General Service | B17: 13.3 | G17: Brake Service | H17: 3
A18: Oil Change | B18: 32.6 | G18: Engine Check | H18: 3
A19: Grand Total | B19: 92.4 | G19: Full Service | H19: 4
G20: General Service | H20: 3
G21: Oil Change | H21: 7
G22: Grand Total | H22: 20

Sheet Revenue&Profit
A3: Row Labels | B3: Sum of Revenue | C3: Sum of Cost | D3: Sum of Profit | M3: Row Labels | N3: Sum of Profit
A4: BMW | B4: 240000 | C4: 192000 | D4: 48000 | M4: BMW | N4: 48000
A5: Ford | B5: 160000 | C5: 132000 | D5: 28000 | M5: Ford | N5: 28000
A6: Honda | B6: 112000 | C6: 88000 | D6: 24000 | M6: Honda | N6: 24000
A7: Hyundai | B7: 100000 | C7: 80000 | D7: 20000 | M7: Hyundai | N7: 20000
A8: Toyota | B8: 120000 | C8: 96000 | D8: 24000 | M8: Toyota | N8: 24000
A9: Grand Total | B9: 732000 | C9: 588000 | D9: 144000 | M9: Grand Total | N9: 144000
A16: Row Labels | B16: Sum of Revenue | C16: Sum of Profit
A17: BMW | B17: 240000 | C17: 48000
A18: Ford | B18: 160000 | C18: 28000
A19: Honda | B19: 112000 | C19: 24000
A20: Hyundai | B20: 100000 | C20: 20000
A21: Toyota | B21: 120000 | C21: 24000
A22: Grand Total | B22: 732000 | C22: 144000

Sheet MainDashboard
A1: AutoMobile Sales Analytics
B6: TOTAL UNITS SOLD | E6: Total Revenue | H6: Total Cost | K6: Total Profit | N6: Average CSAT
B7: =GETPIVOTDATA("Sum of Units Sold",KPIBackend!$A$3) -> 20 | E7: =GETPIVOTDATA("Revenue",KPIBackend!$A$3) -> 732000 | H7: =GETPIVOTDATA("Sum of Cost",KPIBackend!$A$3) -> 588000 | K7: =GETPIVOTDATA("Sum of Profit",KPIBackend!$A$3) -> 144000 | N7: =GETPIVOTDATA("Average of CSAT Score",KPIBackend!$A$3) -> 4.62
E32: .

Sheet KPIBackend
A3: Sum of Revenue | B3: Sum of Units Sold | C3: Sum of Cost | D3: Sum of Profit | E3: Average of CSAT Score
A4: 732000 | B4: 20 | C4: 588000 | D4: 144000 | E4: 4.62

Sheet TableAutomobileSales
A1: Sale ID | B1: Sale Date | C1: Year | D1: Month | E1: Region | F1: Dealer ID | G1: Dealer Name | H1: Brand | I1: Model | J1: Category | K1: Customer ID | L1: Customer Age | M1: Gender | N1: Income | O1: Occupation | P1: Units Sold | Q1: Selling Price | R1: Revenue | S1: Cost | T1: Profit | U1: Target Units | V1: Target Achievement % | W1: Service Type | X1: Service Cost | Y1: CSAT Score
A2: S001 | B2: 46027 | C2: 2026 | D2: January | E2: North | F2: DLR-01 | G2: Apex Motors | H2: Toyota | I2: RAV4 | J2: Mass Market | K2: C001 | L2: 32 | M2: Male | N2: 65000 | O2: IT | P2: 1 | Q2: 30000 | R2: =Table2[[#This Row],[Units Sold]]*Table2[[#This Row],[Selling Price]] -> 30000 | S2: 24000 | T2: =R2-S2 -> 6000 | U2: 1000 | V2: 1 | W2: Oil Change | X2: 150 | Y2: 4.8
A3: S002 | B3: 46034 | C3: 2026 | D3: January | E3: South | F3: DLR-02 | G3: Prime Auto | H3: Honda | I3: CR-V | J3: Mass Market | K3: C002 | L3: 41 | M3: Female | N3: 72000 | O3: Manager | P3: 1 | Q3: 28000 | R3: =Table2[[#This Row],[Units Sold]]*Table2[[#This Row],[Selling Price]] -> 28000 | S3: 22000 | T3: =R3-S3 -> 6000 | U3: 900 | V3: 1 | W3: General Service | X3: 250 | Y3: 4.5
A4: S003 | B4: 46040 | C4: 2026 | D4: January | E4: East | F4: DLR-03 | G4: Metro Wheels | H4: Ford | I4: F-150 | J4: Truck | K4: C003 | L4: 38 | M4: Male | N4: 85000 | O4: Business | P4: 1 | Q4: 40000 | R4: =Table2[[#This Row],[Units Sold]]*Table2[[#This Row],[Selling Price]] -> 40000 | S4: 33000 | T4: =R4-S4 -> 7000 | U4: 800 | V4: 1 | W4: Engine Check | X4: 300 | Y4: 4.6
A5: S004 | B5: 46047 | C5: 2026 | D5: January | E5: West | F5: DLR-04 | G5: Royal Motors | H5: Hyundai | I5: Tucson | J5: Mass Market | K5: C004 | L5: 29 | M5: Female | N5: 55000 | O5: Teacher | P5: 1 | Q5: 25000 | R5: =Table2[[#This Row],[Units Sold]]*Table2[[#This Row],[Selling Price]] -> 25000 | S5: 20000 | T5: =R5-S5 -> 5000 | U5: 1200 | V5: 1 | W5: Oil Change | X5: 150 | Y5: 4.7
A6: S005 | B6: 46056 | C6: 2026 | D6: February | E6: North | F6: DLR-01 | G6: Apex Motors | H6: BMW | I6: X5 | J6: Luxury | K6: C005 | L6: 45 | M6: Male | N6: 120000 | O6: Business | P6: 1 | Q6: 60000 | R6: =Table2[[#This Row],[Units Sold]]*Table2[[#This Row],[Selling Price]] -> 60000 | S6: 48000 | T6: =R6-S6 -> 12000 | U6: 1000 | V6: 1 | W6: Full Service | X6: 500 | Y6: 4.9
A7: S006 | B7: 46063 | C7: 2026 | D7: February | E7: South | F7: DLR-02 | G7: Prime Auto | H7: Toyota | I7: RAV4 | J7: Mass Market | K7: C006 | L7: 36 | M7: Female | N7: 68000 | O7: Doctor | P7: 1 | Q7: 30000 | R7: =Table2[[#This Row],[Units Sold]]*Table2[[#This Row],[Selling Price]] -> 30000 | S7: 24000 | T7: =R7-S7 -> 6000 | U7: 900 | V7: 1 | W7: Brake Service | X7: 350 | Y7: 4.6
A8: S007 | B8: 46069 | C8: 2026 | D8: February | E8: East | F8: DLR-03 | G8: Metro Wheels | H8: Honda | I8: CR-V | J8: Mass Market | K8: C007 | L8: 27 | M8: Male | N8: 48000 | O8: Engineer | P8: 1 | Q8: 28000 | R8: =Table2[[#This Row],[Units Sold]]*Table2[[#This Row],[Selling Price]] -> 28000 | S8: 22000 | T8: =R8-S8 -> 6000 | U8: 6000 | V8: 1 | W8: Oil Change | X8: 150 | Y8: 4.4
A9: S008 | B9: 46077 | C9: 2026 | D9: February | E9: West | F9: DLR-04 | G9: Royal Motors | H9: Ford | I9: F-150 | J9: Truck | K9: C008 | L9: 51 | M9: Male | N9: 95000 | O9: Business | P9: 1 | Q9: 40000 | R9: =Table2[[#This Row],[Units Sold]]*Table2[[#This Row],[Selling Price]] -> 40000 | S9: 33000 | T9: =R9-S9 -> 7000 | U9: 700 | V9: 1 | W9: General Service | X9: 250 | Y9: 4.3
A10: S009 | B10: 46086 | C10: 2026 | D10: March | E10: North | F10: DLR-05 | G10: Speed Auto | H10: Hyundai | I10: Tucson | J10: Mass Market | K10: C009 | L10: 34 | M10: Female | N10: 62000 | O10: Designer | P10: 1 | Q10: 25000 | R10: =Table2[[#This Row],[Units Sold]]*Table2[[#This Row],[Selling Price]] -> 25000 | S10: 20000 | T10: =R10-S10 -> 5000 | U10: 750 | V10: 1 | W10: Oil Change | X10: 150 | Y10: 4.7
A11: S010 | B11: 46095 | C11: 2026 | D11: March | E11: South | F11: DLR-06 | G11: Star Motors | H11: BMW | I11: X5 | J11: Mass Market | K11: C010 | L11: 43 | M11: Male | N11: 110000 | O11: Manager | P11: 1 | Q11: 60000 | R11: =Table2[[#This Row],[Units Sold]]*Table2[[#This Row],[Selling Price]] -> 60000 | S11: 48000 | T11: =R11-S11 -> 12000 | U11: 1100 | V11: 1 | W11: Full Service | X11: 500 | Y11: 4.8
A12: S011 | B12: 46103 | C12: 2026 | D12: March | E12: East | F12: DLR-07 | G12: United Wheels | H12: Toyota | I12: RAV4 | J12: Mass Market | K12: C011 | L12: 31 | M12: Male | N12: 58000 | O12: Engineer | P12: 1 | Q12: 30000 | R12: =Table2[[#This Row],[Units Sold]]*Table2[[#This Row],[Selling Price]] -> 30000 | S12: 24000 | T12: =R12-S12 -> 6000 | U12: 700 | V12: 1 | W12: Oil Change | X12: 150 | Y12: 4.5
A13: S012 | B13: 46110 | C13: 2026 | D13: March | E13: West | F13: DLR-08 | G13: City Auto | H13: Honda | I13: CR-V | J13: Mass Market | K13: C012 | L13: 39 | M13: Female | N13: 70000 | O13: Doctor | P13: 1 | Q13: 28000 | R13: =Table2[[#This Row],[Units Sold]]*Table2[[#This Row],[Selling Price]] -> 28000 | S13: 22000 | T13: =R13-S13 -> 6000 | U13: 850 | V13: 1 | W13: Brake Service | X13: 350 | Y13: 4.6
... A21: S020 | B21: 46173 | C21: 2026 | D21: May | E21: West | F21: DLR-04 | G21: Royal Motors | H21: BMW | I21: X5 | J21: Luxury | K21: C020 | L21: 46 | M21: Male | N21: 115000 | O21: Manager | P21: 1 | Q21: 60000 | R21: =Table2[[#This Row],[Units Sold]]*Table2[[#This Row],[Selling Price]] -> 60000 | S21: 48000 | T21: =R21-S21 -> 12000 | U21: 1200 | V21: 1 | W21: Full Service | X21: 500 | Y21: 4.9

Sheet MainDashborad2
